dorian/__init__.py
dorian/constants.py
dorian/cosmology.py
dorian/gadget.py
dorian/healpix.py
dorian/misc.py
dorian/parallel_transport.py
dorian/peaks.py
dorian/power_spectrum.py
dorian/raytracing.py
dorian_astro-0.0.1.dist-info/LICENSE
dorian_astro-0.0.1.dist-info/METADATA
dorian_astro-0.0.1.dist-info/WHEEL
dorian_astro-0.0.1.dist-info/top_level.txt
dorian_astro-0.0.1.dist-info/RECORD
