Metadata-Version: 2.1
Name: dorian-astro
Version: 0.0.1
Summary: Code to generate full-sky ray-traced weak gravitational lensing maps from cosmological simulations.
Home-page: https://gitlab.mpcdf.mpg.de/fferlito/dorian
Author: Fulvio Ferlito
Author-email: fulvioferlito@gmail.com
License: GPLv3
Requires-Python: >=3.8
License-File: LICENSE
Requires-Dist: numpy
Requires-Dist: scipy
Requires-Dist: healpy
Requires-Dist: h5py
Requires-Dist: ducc0
